baidu/__init__.py
baidu/exceptions.py
baidu/api/__init__.py
baidu/client/__init__.py
baidu/session/__init__.py
baidu/session/memorystorage.py
baidu/session/redisstorage.py
baidu_api-0.0.2.dist-info/LICENSE
baidu_api-0.0.2.dist-info/METADATA
baidu_api-0.0.2.dist-info/WHEEL
baidu_api-0.0.2.dist-info/top_level.txt
baidu_api-0.0.2.dist-info/RECORD
