Metadata-Version: 2.1
Name: baidu-api
Version: 0.0.2
Summary: the python sdk for baidu
Home-page: https://github.com/ramwin/baidu-api
Author: Xiang Wang
Author-email: ramwin@qq.com
License: UNKNOWN
Platform: UNKNOWN
Classifier: Programming Language :: Python :: 2
Classifier: Programming Language :: Python :: 3
Classifier: License :: OSI Approved :: MIT License
Classifier: Operating System :: OS Independent
Requires-Python: >=3.5
Requires-Dist: redis
Requires-Dist: requests
